IM_algorithm/__init__.py
IM_algorithm/heuristic_algorithm/__init__.py
IM_algorithm/heuristic_algorithm/heuristic_algorithm.py
IM_algorithm/simulation_algorithm/__init__.py
IM_algorithm/simulation_algorithm/simulation_algorithm.py
decorators/__init__.py
decorators/decorators.py
epidemic_model/__init__.py
epidemic_model/epidemic_model.py
graph_embedding/__init__.py
graph_embedding/graph_embedding.py
nn/__init__.py
nn/gcncov.py
propagation_model/__init__.py
propagation_model/propagation_model.py
utils/__init__.py
utils/utils.py
PyInfluenceMaximum-0.0.1.dist-info/LICENSE
PyInfluenceMaximum-0.0.1.dist-info/METADATA
PyInfluenceMaximum-0.0.1.dist-info/WHEEL
PyInfluenceMaximum-0.0.1.dist-info/top_level.txt
PyInfluenceMaximum-0.0.1.dist-info/RECORD
